MOdel/__init__.py
MOdel/load_model.py
MOdel/test.py
mlmodel_package-0.1.dist-info/LICENSE
mlmodel_package-0.1.dist-info/METADATA
mlmodel_package-0.1.dist-info/WHEEL
mlmodel_package-0.1.dist-info/top_level.txt
mlmodel_package-0.1.dist-info/RECORD
